LICENSE
MANIFEST.in
README.rst
setup.cfg
setup.py
versioneer.py
tpDcc/__init__.py
tpDcc/libs/__init__.py
tpDcc/libs/nameit/__init__.py
tpDcc/libs/nameit/__logging__.ini
tpDcc/libs/nameit/__version__.py
tpDcc/libs/nameit/_version.py
tpDcc/libs/nameit/core/__init__.py
tpDcc/libs/nameit/core/consts.py
tpDcc/libs/nameit/core/namelib.py
tpDcc/libs/nameit/externals/__init__.py
tpDcc/libs/nameit/externals/lucidity/__init__.py
tpDcc/libs/nameit/externals/lucidity/_version.py
tpDcc/libs/nameit/externals/lucidity/error.py
tpDcc/libs/nameit/externals/lucidity/template.py
tpDcc_libs_nameit.egg-info/PKG-INFO
tpDcc_libs_nameit.egg-info/SOURCES.txt
tpDcc_libs_nameit.egg-info/dependency_links.txt
tpDcc_libs_nameit.egg-info/not-zip-safe
tpDcc_libs_nameit.egg-info/requires.txt
tpDcc_libs_nameit.egg-info/top_level.txt