Metadata-Version: 2.1
Name: tpDcc-libs-nameit
Version: 0.0.10
Summary: Python module that manages the nomenclature of your pipelines.
Home-page: https://github.com/tpDcc/tpDcc-libs-nameit
Author: Tomas Poveda
Author-email: tpovedatd@gmail.com
License: MIT
Platform: UNKNOWN
Provides-Extra: dev
Provides-Extra: test
